dataload/__init__.py
dataload/config.py
dataload/main.py
dataload/application/__init__.py
dataload/application/services/__init__.py
dataload/application/services/error_handling.py
dataload/application/services/embedding/__init__.py
dataload/application/services/embedding/bedrock_provider.py
dataload/application/services/embedding/embedding_provider.py
dataload/application/services/embedding/gemini_provider.py
dataload/application/services/embedding/openai_provider.py
dataload/application/services/embedding/sentence_transformers_provider.py
dataload/application/services/validation/__init__.py
dataload/application/services/validation/case_sensitivity_validator.py
dataload/application/services/validation/data_type_validator.py
dataload/application/services/validation/schema_validator.py
dataload/application/services/validation/validation_service.py
dataload/application/use_cases/__init__.py
dataload/application/use_cases/data_loader_use_case.py
dataload/application/use_cases/data_move_use_case.py
dataload/application/use_cases/data_updater_use_case.py
dataload/domain/__init__.py
dataload/domain/entities.py
dataload/infrastructure/__init__.py
dataload/infrastructure/db/__init__.py
dataload/infrastructure/db/data_repository.py
dataload/infrastructure/db/db_connection.py
dataload/infrastructure/db/postgres_data_move_repository.py
dataload/infrastructure/storage/__init__.py
dataload/infrastructure/storage/loaders.py
dataload/infrastructure/vector_stores/__init__.py
dataload/infrastructure/vector_stores/chroma_store.py
dataload/infrastructure/vector_stores/faiss_store.py
dataload/interfaces/__init__.py
dataload/interfaces/data_move_repository.py
dataload/interfaces/embedding_provider.py
dataload/interfaces/storage_loader.py
dataload/interfaces/vector_store.py
vector_dataloader-1.2.5.dist-info/METADATA
vector_dataloader-1.2.5.dist-info/WHEEL
vector_dataloader-1.2.5.dist-info/entry_points.txt
vector_dataloader-1.2.5.dist-info/top_level.txt
vector_dataloader-1.2.5.dist-info/RECORD
