Metadata-Version: 2.4
Name: vector-dataloader
Version: 1.2.5
Summary: Production-grade embedding loader for CSV data to vector stores with multiple providers.
Author-email: Shashwat Roy <shashwatunf@gmail.com>
License: MIT
Classifier: Development Status :: 5 - Production/Stable
Classifier: Intended Audience :: Developers
Classifier: License :: OSI Approved :: MIT License
Classifier: Programming Language :: Python :: 3.11
Classifier: Programming Language :: Python :: 3.12
Classifier: Programming Language :: Python :: 3.13
Requires-Python: <3.14,>=3.11
Requires-Dist: boto3>=1.35.46
Requires-Dist: asyncpg>=0.30.0
Requires-Dist: pgvector>=0.4.1
Requires-Dist: pandas>=2.3.3
Requires-Dist: pydantic>=2.11.10
Requires-Dist: tenacity>=9.1.2
Requires-Dist: numpy>=2.3.3
Requires-Dist: anyio>=4.11.0
Requires-Dist: python-dotenv>=1.1.1
Provides-Extra: gemini
Requires-Dist: google-genai>=1.1.0; extra == "gemini"
Provides-Extra: sentence-transformers
Requires-Dist: sentence-transformers>=5.1.1; extra == "sentence-transformers"
Requires-Dist: torch>=2.8.0; extra == "sentence-transformers"
Provides-Extra: openai
Requires-Dist: openai>=2.2.0; extra == "openai"
Provides-Extra: faiss
Requires-Dist: faiss-cpu>=1.12.0; extra == "faiss"
Provides-Extra: chroma
Requires-Dist: chromadb>=1.1.1; extra == "chroma"
Requires-Dist: posthog<6.0.0,>=5.0.0; extra == "chroma"
Provides-Extra: dev
Requires-Dist: pytest>=8.4.2; extra == "dev"
Requires-Dist: pytest-asyncio>=1.2.0; extra == "dev"
Requires-Dist: black>=25.9.0; extra == "dev"
Provides-Extra: all
Requires-Dist: google-genai>=1.1.0; extra == "all"
Requires-Dist: sentence-transformers>=5.1.1; extra == "all"
Requires-Dist: torch>=2.8.0; extra == "all"
Requires-Dist: openai>=2.2.0; extra == "all"
Requires-Dist: faiss-cpu>=1.12.0; extra == "all"
Requires-Dist: chromadb>=1.1.1; extra == "all"
Requires-Dist: posthog<6.0.0,>=5.0.0; extra == "all"
